keyvault_env/__init__.py
keyvault_env/cli.py
keyvault_env/core.py
keyvault_env-1.0.5.dist-info/licenses/LICENSE
keyvault_env-1.0.5.dist-info/METADATA
keyvault_env-1.0.5.dist-info/WHEEL
keyvault_env-1.0.5.dist-info/top_level.txt
keyvault_env-1.0.5.dist-info/RECORD
