Metadata-Version: 2.4
Name: keyvault-env
Version: 1.0.5
Summary: Upload secrets from a .env file to Azure Key Vault and fetch them easily.
Author-email: Hrishikesh Kalola <hackathon.hrishi@gmail.com>, Dhiraj Kumar <salesforce.dhiraj@gmail.com>
License: MIT
Project-URL: Dhiraj-LinkedIn, https://www.linkedin.com/in/ai-dhiraj/
Project-URL: Dhiraj-Github, https://github.com/airanger-paperchase
Project-URL: Hrishikesh-LinkedIn, https://www.linkedin.com/in/hrishk/
Project-URL: Hrishikesh-GitHub, https://github.com/hrishi-008
Requires-Python: >=3.8
License-File: LICENSE
Requires-Dist: azure-identity>=1.12.0
Requires-Dist: azure-keyvault-secrets>=4.6.0
Requires-Dist: python-dotenv>=1.0.0
Dynamic: license-file
